{
  "edges": [
    {
      "causal_link_type": "DIRECT",
      "description": "Abnormal cartilage calcification and endochondral ossification produce the characteristic short tibiae, short metacarpals, and vertebral abnormalities.",
      "is_orphan": false,
      "predicate": "causes",
      "source": "Abnormal Cartilage Calcification and Endochondral Ossification",
      "target": "Disproportionate Limb and Vertebral Skeletal Pattern"
    },
    {
      "causal_link_type": "DIRECT",
      "description": "Abnormal cartilage calcification produces punctate epiphyseal calcifications.",
      "is_orphan": false,
      "predicate": "causes",
      "source": "Disproportionate Limb and Vertebral Skeletal Pattern",
      "target": "Epiphyseal Stippling"
    },
    {
      "causal_link_type": "DIRECT",
      "description": "The limb skeletal pattern includes short central metacarpals.",
      "is_orphan": false,
      "predicate": "causes",
      "source": "Disproportionate Limb and Vertebral Skeletal Pattern",
      "target": "Short Metacarpals"
    },
    {
      "causal_link_type": "DIRECT",
      "description": "The dysplasia includes craniofacial skeletal involvement with flat midface and nose.",
      "is_orphan": false,
      "predicate": "causes",
      "source": "Disproportionate Limb and Vertebral Skeletal Pattern",
      "target": "Depressed Nasal Bridge and Flat Midface"
    },
    {
      "causal_link_type": "DIRECT",
      "description": "The named skeletal pattern includes short tibiae.",
      "is_orphan": false,
      "predicate": "causes",
      "source": "Disproportionate Limb and Vertebral Skeletal Pattern",
      "target": "Short Tibia"
    },
    {
      "causal_link_type": "DIRECT",
      "description": "Vertebral involvement in the skeletal pattern produces coronal cleft vertebrae.",
      "is_orphan": false,
      "predicate": "causes",
      "source": "Disproportionate Limb and Vertebral Skeletal Pattern",
      "target": "Coronal Cleft Vertebrae"
    },
    {
      "causal_link_type": "DIRECT",
      "description": "Disproportionate skeletal growth can produce persistent short stature.",
      "is_orphan": false,
      "predicate": "causes",
      "source": "Disproportionate Limb and Vertebral Skeletal Pattern",
      "target": "Short Stature"
    },
    {
      "causal_link_type": "INDIRECT_KNOWN_INTERMEDIATES",
      "description": "Skeletal dysplasia can complicate joint mobility and produce progressive limitations.",
      "intermediate_mechanisms": [
        "Dysplastic short-limbed skeletal development with contracture or joint limitation."
      ],
      "is_orphan": false,
      "predicate": "causes",
      "source": "Disproportionate Limb and Vertebral Skeletal Pattern",
      "target": "Joint Limitation"
    },
    {
      "causal_link_type": "INDIRECT_KNOWN_INTERMEDIATES",
      "description": "The lower-limb skeletal pattern predisposes to recurrent patellar instability.",
      "intermediate_mechanisms": [
        "Lower-limb dysplasia and altered patellofemoral alignment."
      ],
      "is_orphan": false,
      "predicate": "causes",
      "source": "Disproportionate Limb and Vertebral Skeletal Pattern",
      "target": "Recurrent Patellar Dislocation"
    },
    {
      "causal_link_type": "DIRECT",
      "description": "Vertebral-body involvement in CDP-TM produces platyspondyly.",
      "is_orphan": false,
      "predicate": "causes",
      "source": "Disproportionate Limb and Vertebral Skeletal Pattern",
      "target": "Platyspondyly"
    },
    {
      "causal_link_type": "DIRECT",
      "description": "The long-bone skeletal pattern includes bowed humeri.",
      "is_orphan": false,
      "predicate": "causes",
      "source": "Disproportionate Limb and Vertebral Skeletal Pattern",
      "target": "Bowing of the Humerus"
    },
    {
      "causal_link_type": "INDIRECT_UNKNOWN_INTERMEDIATES",
      "description": "The skeletal dysplasia can involve the hips and require orthopedic intervention.",
      "is_orphan": false,
      "predicate": "causes",
      "source": "Disproportionate Limb and Vertebral Skeletal Pattern",
      "target": "Hip Dysplasia"
    },
    {
      "causal_link_type": "INDIRECT_UNKNOWN_INTERMEDIATES",
      "description": "Chronic serous otitis media is observed in CDP-TM, but the specific intermediate mechanism is not resolved.",
      "is_orphan": false,
      "predicate": "causes",
      "source": "Disproportionate Limb and Vertebral Skeletal Pattern",
      "target": "Chronic Serous Otitis Media"
    },
    {
      "causal_link_type": "INDIRECT_KNOWN_INTERMEDIATES",
      "description": "Vertebral skeletal involvement can progress to spinal canal stenosis.",
      "intermediate_mechanisms": [
        "Vertebral skeletal dysplasia and spinal canal narrowing."
      ],
      "is_orphan": false,
      "predicate": "causes",
      "source": "Disproportionate Limb and Vertebral Skeletal Pattern",
      "target": "Spinal Stenosis"
    },
    {
      "is_orphan": false,
      "predicate": "treats",
      "source": "Orthopedic and Spine Surveillance",
      "target": "Spinal Stenosis"
    }
  ],
  "nodes": [
    {
      "color": "#dbeafe",
      "description": "CDP-TM affects growth plate and epiphyseal cartilage, producing punctate calcifications, vertebral clefts, and later abnormal metaphyseal or epiphyseal morphology as calcifications remodel.",
      "id": "Abnormal Cartilage Calcification and Endochondral Ossification",
      "is_orphan": false,
      "meta": {
        "biological_processes": [
          "cartilage development",
          "cartilage development involved in endochondral bone morphogenesis",
          "bone mineralization"
        ],
        "cell_types": [
          "chondrocyte",
          "growth plate cartilage chondrocyte"
        ],
        "evidence": [
          {
            "reference": "PMID:2248286",
            "reference_title": "Chondrodysplasia punctata, tibia-metacarpal (MT) type.",
            "snippet": "Consistent radiologic manifestations in the newborn infant are discrete calcific stippling, coronal clefts of vertebral bodies, short tibiae, and shortness of the 2nd and 3rd metacarpal bones.",
            "supports": "SUPPORT"
          }
        ],
        "evidence_count": 1
      },
      "node_type": "pathophysiology"
    },
    {
      "color": "#fef3c7",
      "description": "The humeri can be markedly short and bowed in CDP-TM, as seen on prenatal CT and postnatal radiographs.\n",
      "id": "Bowing of the Humerus",
      "is_orphan": false,
      "meta": {
        "evidence": [
          {
            "reference": "PMID:17805524",
            "reference_title": "Prenatal diagnosis of chondrodysplasia punctata tibia-metacarpal type using multidetector CT and three-dimensional reconstruction.",
            "snippet": "the tibiae were much shorter than the fibulae, the humeri were very short and bowed, and severe platyspondyly was evident.",
            "supports": "SUPPORT"
          }
        ],
        "evidence_count": 1,
        "term_id": "HP:0006488"
      },
      "node_type": "phenotype"
    },
    {
      "color": "#fef3c7",
      "description": "Chronic serous otitis media requiring surgical drainage tubes has been observed in CDP-TM during childhood.\n",
      "id": "Chronic Serous Otitis Media",
      "is_orphan": false,
      "meta": {
        "evidence": [
          {
            "reference": "PMID:14699613",
            "reference_title": "Longterm follow-up in chondrodysplasia punctata, tibia-metacarpal type, demonstrating natural history.",
            "snippet": "Two patients had chronic serous otitis media requiring tympanostomy tubes during childhood.",
            "supports": "SUPPORT"
          }
        ],
        "evidence_count": 1,
        "term_id": "HP:0000405"
      },
      "node_type": "phenotype"
    },
    {
      "color": "#fef3c7",
      "description": "Vertebral coronal clefts are part of the newborn radiographic pattern.",
      "id": "Coronal Cleft Vertebrae",
      "is_orphan": false,
      "meta": {
        "evidence": [
          {
            "reference": "PMID:2248286",
            "reference_title": "Chondrodysplasia punctata, tibia-metacarpal (MT) type.",
            "snippet": "Consistent radiologic manifestations in the newborn infant are discrete calcific stippling, coronal clefts of vertebral bodies, short tibiae, and shortness of the 2nd and 3rd metacarpal bones.",
            "supports": "SUPPORT"
          }
        ],
        "evidence_count": 1,
        "term_id": "HP:0003417"
      },
      "node_type": "phenotype"
    },
    {
      "color": "#fef3c7",
      "description": "Flat midface and nose are principal clinical manifestations of the disorder.",
      "id": "Depressed Nasal Bridge and Flat Midface",
      "is_orphan": false,
      "meta": {
        "evidence": [
          {
            "reference": "PMID:2248286",
            "reference_title": "Chondrodysplasia punctata, tibia-metacarpal (MT) type.",
            "snippet": "Its principal clinical manifestations are flat midface and nose, short limbs, and otherwise normal development.",
            "supports": "SUPPORT"
          }
        ],
        "evidence_count": 1,
        "term_id": "HP:0005280"
      },
      "node_type": "phenotype"
    },
    {
      "color": "#dbeafe",
      "description": "The disorder produces short tibiae, short second to fourth metacarpals, vertebral clefts, and variable later orthopedic complications.",
      "id": "Disproportionate Limb and Vertebral Skeletal Pattern",
      "is_orphan": false,
      "meta": {
        "biological_processes": [
          "bone development"
        ],
        "evidence": [
          {
            "reference": "PMID:2248286",
            "reference_title": "Chondrodysplasia punctata, tibia-metacarpal (MT) type.",
            "snippet": "Radiologic findings in the older child include shortness of tibiae and the 3rd and 4th metacarpals.",
            "supports": "SUPPORT"
          }
        ],
        "evidence_count": 1
      },
      "node_type": "pathophysiology"
    },
    {
      "color": "#fef3c7",
      "description": "Punctate epiphyseal calcifications are the hallmark early radiologic finding.",
      "id": "Epiphyseal Stippling",
      "is_orphan": false,
      "meta": {
        "evidence": [
          {
            "reference": "PMID:2248286",
            "reference_title": "Chondrodysplasia punctata, tibia-metacarpal (MT) type.",
            "snippet": "Consistent radiologic manifestations in the newborn infant are discrete calcific stippling, coronal clefts of vertebral bodies, short tibiae, and shortness of the 2nd and 3rd metacarpal bones.",
            "supports": "SUPPORT"
          }
        ],
        "evidence_count": 1,
        "term_id": "HP:0010655"
      },
      "node_type": "phenotype"
    },
    {
      "color": "#fef3c7",
      "description": "Hip dysplasia requiring orthopedic intervention is a recognized long-term complication of CDP-TM.\n",
      "id": "Hip Dysplasia",
      "is_orphan": false,
      "meta": {
        "evidence": [
          {
            "reference": "PMID:14699613",
            "reference_title": "Longterm follow-up in chondrodysplasia punctata, tibia-metacarpal type, demonstrating natural history.",
            "snippet": "One patient had hip dysplasia requiring orthopedic surgical intervention. All patients had recurrent patella dislocation.",
            "supports": "SUPPORT"
          }
        ],
        "evidence_count": 1,
        "term_id": "HP:0001385"
      },
      "node_type": "phenotype"
    },
    {
      "color": "#fef3c7",
      "description": "Joint contractures or progressive limitations can complicate the skeletal dysplasia.",
      "id": "Joint Limitation",
      "is_orphan": false,
      "meta": {
        "evidence": [
          {
            "reference": "PMID:18713450",
            "reference_title": "Progressive joint limitations as the first alarming signs in a boy with short - limbed dwarfism: A case report.",
            "snippet": "CASE PRESENTATION: We report on a 5-year-old boy of Austrian origin who manifests progressive joint limitations in connection with a dysplastic form of short-limbed dwarfism namely chondrodysplasia punctata-tibial-metacarpal-type.",
            "supports": "SUPPORT"
          }
        ],
        "evidence_count": 1,
        "term_id": "HP:0001371"
      },
      "node_type": "phenotype"
    },
    {
      "color": "#fce7f3",
      "description": "Management is supportive and complication-directed, including monitoring for spinal stenosis, patellar dislocation, hip dysplasia, and other orthopedic complications.",
      "id": "Orthopedic and Spine Surveillance",
      "is_orphan": false,
      "meta": {
        "evidence": [
          {
            "reference": "PMID:14699613",
            "reference_title": "Longterm follow-up in chondrodysplasia punctata, tibia-metacarpal type, demonstrating natural history.",
            "snippet": "One patient had hip dysplasia requiring orthopedic surgical intervention. All patients had recurrent patella dislocation.",
            "supports": "SUPPORT"
          }
        ],
        "evidence_count": 1
      },
      "node_type": "treatment"
    },
    {
      "color": "#fef3c7",
      "description": "Flattened vertebral bodies (platyspondyly) are observed on neonatal and prenatal imaging and may partially resolve with growth.\n",
      "id": "Platyspondyly",
      "is_orphan": false,
      "meta": {
        "evidence": [
          {
            "reference": "PMID:17805524",
            "reference_title": "Prenatal diagnosis of chondrodysplasia punctata tibia-metacarpal type using multidetector CT and three-dimensional reconstruction.",
            "snippet": "the tibiae were much shorter than the fibulae, the humeri were very short and bowed, and severe platyspondyly was evident.",
            "supports": "SUPPORT"
          }
        ],
        "evidence_count": 1,
        "term_id": "HP:0000926"
      },
      "node_type": "phenotype"
    },
    {
      "color": "#fef3c7",
      "description": "Recurrent patellar dislocation is a persistent orthopedic complication.",
      "id": "Recurrent Patellar Dislocation",
      "is_orphan": false,
      "meta": {
        "evidence": [
          {
            "reference": "PMID:14699613",
            "reference_title": "Longterm follow-up in chondrodysplasia punctata, tibia-metacarpal type, demonstrating natural history.",
            "snippet": "All patients had recurrent patella dislocation.",
            "supports": "SUPPORT"
          }
        ],
        "evidence_count": 1,
        "term_id": "HP:0005001"
      },
      "node_type": "phenotype"
    },
    {
      "color": "#fef3c7",
      "description": "Short metacarpals, especially central metacarpals, are a defining hand feature.",
      "id": "Short Metacarpals",
      "is_orphan": false,
      "meta": {
        "evidence": [
          {
            "reference": "PMID:2248286",
            "reference_title": "Chondrodysplasia punctata, tibia-metacarpal (MT) type.",
            "snippet": "Radiologic findings in the older child include shortness of tibiae and the 3rd and 4th metacarpals.",
            "supports": "SUPPORT"
          }
        ],
        "evidence_count": 1,
        "term_id": "HP:0010049"
      },
      "node_type": "phenotype"
    },
    {
      "color": "#fef3c7",
      "description": "Disproportionate short stature can persist into adulthood.",
      "id": "Short Stature",
      "is_orphan": false,
      "meta": {
        "evidence": [
          {
            "reference": "PMID:14699613",
            "reference_title": "Longterm follow-up in chondrodysplasia punctata, tibia-metacarpal type, demonstrating natural history.",
            "snippet": "The patients attained adult heights of 152, 138, and 148 cm.",
            "supports": "SUPPORT"
          }
        ],
        "evidence_count": 1,
        "term_id": "HP:0004322"
      },
      "node_type": "phenotype"
    },
    {
      "color": "#fef3c7",
      "description": "Short tibiae are part of the named pattern and can be marked on prenatal imaging.",
      "id": "Short Tibia",
      "is_orphan": false,
      "meta": {
        "evidence": [
          {
            "reference": "PMID:17805524",
            "reference_title": "Prenatal diagnosis of chondrodysplasia punctata tibia-metacarpal type using multidetector CT and three-dimensional reconstruction.",
            "snippet": "On 3-D CT, the tibiae were much shorter than the fibulae, the humeri were very short and bowed, and severe platyspondyly was evident.",
            "supports": "SUPPORT"
          }
        ],
        "evidence_count": 1,
        "term_id": "HP:0005736"
      },
      "node_type": "phenotype"
    },
    {
      "color": "#fef3c7",
      "description": "Lumbar spinal stenosis can develop as a late orthopedic complication and may require surgical decompression in adulthood.\n",
      "id": "Spinal Stenosis",
      "is_orphan": false,
      "meta": {
        "evidence": [
          {
            "reference": "PMID:14699613",
            "reference_title": "Longterm follow-up in chondrodysplasia punctata, tibia-metacarpal type, demonstrating natural history.",
            "snippet": "One patient suffered persisting back pain related to spinal stenosis and required lumbar laminectomy at the age of 26 years.",
            "supports": "SUPPORT"
          }
        ],
        "evidence_count": 1,
        "term_id": "HP:0003416"
      },
      "node_type": "phenotype"
    }
  ],
  "orphan_targets": []
}