{
  "edges": [
    {
      "causal_link_type": "INDIRECT_KNOWN_INTERMEDIATES",
      "intermediate_mechanisms": [
        "C1-INH consumption",
        "autoantibody-mediated C1-INH inactivation"
      ],
      "is_orphan": false,
      "predicate": "causes",
      "source": "B-cell Disorder-Associated C1-INH Consumption",
      "target": "Acquired C1 Inhibitor Deficiency"
    },
    {
      "causal_link_type": "DIRECT",
      "is_orphan": false,
      "predicate": "causes",
      "source": "Anti-C1-INH Immune Complex Formation",
      "target": "Acquired C1 Inhibitor Deficiency"
    },
    {
      "causal_link_type": "INDIRECT_KNOWN_INTERMEDIATES",
      "intermediate_mechanisms": [
        "kallikrein-kinin system dysregulation",
        "contact system activation"
      ],
      "is_orphan": false,
      "predicate": "causes",
      "source": "Acquired C1 Inhibitor Deficiency",
      "target": "Bradykinin Excess"
    },
    {
      "causal_link_type": "DIRECT",
      "is_orphan": false,
      "predicate": "causes",
      "source": "Bradykinin Excess",
      "target": "Bradykinin-Driven Vascular Permeability"
    },
    {
      "is_orphan": false,
      "predicate": "targets",
      "source": "Plasma-Derived or Recombinant C1 Inhibitor Concentrate",
      "target": "Acquired C1 Inhibitor Deficiency"
    },
    {
      "is_orphan": false,
      "predicate": "targets",
      "source": "Icatibant On-Demand Therapy",
      "target": "Bradykinin-Driven Vascular Permeability"
    },
    {
      "is_orphan": false,
      "predicate": "targets",
      "source": "Berotralstat Long-Term Prophylaxis",
      "target": "Bradykinin Excess"
    },
    {
      "is_orphan": false,
      "predicate": "targets",
      "source": "Tranexamic Acid Long-Term Prophylaxis",
      "target": "Acquired C1 Inhibitor Deficiency"
    },
    {
      "is_orphan": false,
      "predicate": "targets",
      "source": "Treat Underlying Lymphoproliferative Disease",
      "target": "B-cell Disorder-Associated C1-INH Consumption"
    }
  ],
  "nodes": [
    {
      "color": "#dbeafe",
      "description": "Secondary quantitative or functional C1 inhibitor deficiency reduces physiologic inhibition of complement and kallikrein-kinin/contact pathways.",
      "id": "Acquired C1 Inhibitor Deficiency",
      "is_orphan": false,
      "meta": {
        "biological_processes": [
          "complement activation"
        ],
        "evidence": [
          {
            "reference": "PMID:31397881",
            "reference_title": "Serum complexes between C1INH and C1INH autoantibodies for the diagnosis of acquired angioedema.",
            "snippet": "Acquired angioedema due to C1-inhibitor (C1INH) deficiency (AAE) is caused by secondary C1INH deficiency leading to bradykinin-mediated angioedema episodes.",
            "supports": "SUPPORT"
          },
          {
            "reference": "PMID:33472202",
            "reference_title": "Acquired Angioedema with C1 Inhibitor Deficiency: Occurrence, Clinical Features, and Management: A Nationwide Retrospective Study in the Czech Republic Patients.",
            "snippet": "The inclusion criteria involved recurrent episodes of angioedema with the first manifestation at or after the age of 40, negative family history of angioedema, and C1 inhibitor function 50% or less.",
            "supports": "SUPPORT"
          }
        ],
        "evidence_count": 2
      },
      "node_type": "pathophysiology"
    },
    {
      "color": "#dbeafe",
      "description": "Anti-C1-INH autoantibodies can circulate as free antibodies or as C1-INH/anti-C1-INH complexes, providing a mechanism for functional C1-INH loss and a diagnostic marker in some patients.",
      "id": "Anti-C1-INH Immune Complex Formation",
      "is_orphan": false,
      "meta": {
        "biological_processes": [
          "complement activation, classical pathway"
        ],
        "cell_types": [
          "plasma cell"
        ],
        "evidence": [
          {
            "reference": "PMID:31397881",
            "reference_title": "Serum complexes between C1INH and C1INH autoantibodies for the diagnosis of acquired angioedema.",
            "snippet": "C1INH-antiC1INHAb complexes were found in 18 of 20 of the AAE cases, regardless of the presence or absence of detectable free anti-C1INHAbs.",
            "supports": "SUPPORT"
          },
          {
            "reference": "PMID:36726161",
            "reference_title": "C1-inhibitor/C1-inhibitor antibody complexes in acquired angioedema due to C1-inhibitor deficiency.",
            "snippet": "Free circulating and complex antibodies are in a dynamically changing equilibrium.",
            "supports": "SUPPORT"
          }
        ],
        "evidence_count": 2
      },
      "node_type": "pathophysiology"
    },
    {
      "color": "#dbeafe",
      "description": "B-cell lymphoproliferative disease, monoclonal gammopathy, or related antibody-producing states can drive acquired consumption or neutralization of C1 inhibitor and complement components.",
      "id": "B-cell Disorder-Associated C1-INH Consumption",
      "is_orphan": false,
      "meta": {
        "biological_processes": [
          "complement activation, classical pathway"
        ],
        "cell_types": [
          "B cell",
          "plasma cell"
        ],
        "evidence": [
          {
            "reference": "PMID:30866985",
            "reference_title": "Angioedema due to acquired C1-inhibitor deficiency: spectrum and treatment with C1-inhibitor concentrate.",
            "snippet": "The following underlying disorders were present: monoclonal gammopathy of undetermined significance (47.7%), non-Hodgkin lymphoma (27.3%), anti-C1-INH autoantibodies alone (11.4%), and other conditions (4.5%).",
            "supports": "SUPPORT"
          },
          {
            "reference": "PMID:33472202",
            "reference_title": "Acquired Angioedema with C1 Inhibitor Deficiency: Occurrence, Clinical Features, and Management: A Nationwide Retrospective Study in the Czech Republic Patients.",
            "snippet": "Lymphoid malignancy was identified in 9 patients (64%), monoclonal gammopathy of uncertain significance in 3 (21%), and in 1 patient autoimmune disease (ulcerative colitis) was considered causative (7%).",
            "supports": "SUPPORT"
          }
        ],
        "evidence_count": 2
      },
      "node_type": "pathophysiology"
    },
    {
      "color": "#fce7f3",
      "description": "Berotralstat, an oral kallikrein inhibitor, has limited real-world evidence for off-label long-term prophylaxis in AAE-C1-INH.",
      "id": "Berotralstat Long-Term Prophylaxis",
      "is_orphan": false,
      "meta": {
        "evidence": [
          {
            "reference": "PMID:37914894",
            "reference_title": "A Retrospective Analysis of Long-Term Prophylaxis with Berotralstat in Patients with Hereditary Angioedema and Acquired C1-Inhibitor Deficiency-Real-World Data.",
            "snippet": "After 6 months of treatment, a median decrease of attacks per month was noted for HAE type I patients (3.3 to 1.5) and AAE-C1-INH patients (2.3 to 1.0).",
            "supports": "PARTIAL"
          }
        ],
        "evidence_count": 1,
        "therapeutic_agents": [
          "berotralstat"
        ]
      },
      "node_type": "treatment"
    },
    {
      "color": "#dbeafe",
      "description": "Loss of C1-INH control permits excess bradykinin generation, the proximal mediator of nonhistaminergic angioedema attacks.",
      "id": "Bradykinin Excess",
      "is_orphan": false,
      "meta": {
        "biological_processes": [
          "bradykinin biosynthetic process"
        ],
        "evidence": [
          {
            "reference": "PMID:34956216",
            "reference_title": "Angioedema Without Wheals: Challenges in Laboratorial Diagnosis.",
            "snippet": "Although bradykinin-mediated disease results mainly from disturbance in the kallikrein-kinin system, traditionally complement evaluation has been used for diagnosis.",
            "supports": "SUPPORT"
          }
        ],
        "evidence_count": 1
      },
      "node_type": "pathophysiology"
    },
    {
      "color": "#dbeafe",
      "description": "Excess bradykinin signaling increases endothelial permeability and produces localized, transient plasma extravasation in skin, bowel, and upper-airway tissues.",
      "id": "Bradykinin-Driven Vascular Permeability",
      "is_orphan": false,
      "meta": {
        "biological_processes": [
          "positive regulation of vascular permeability"
        ],
        "cell_types": [
          "endothelial cell"
        ],
        "evidence": [
          {
            "reference": "PMID:34956216",
            "reference_title": "Angioedema Without Wheals: Challenges in Laboratorial Diagnosis.",
            "snippet": "They present with subcutaneous and mucosal swellings, affecting extremities, face, genitals, bowels, and upper airways.",
            "supports": "SUPPORT"
          }
        ],
        "evidence_count": 1,
        "locations": [
          "face",
          "larynx",
          "digestive tract"
        ]
      },
      "node_type": "pathophysiology"
    },
    {
      "color": "#fce7f3",
      "description": "Icatibant blocks bradykinin B2 receptor signaling and is used as on-demand treatment for acute AAE-C1-INH attacks.",
      "id": "Icatibant On-Demand Therapy",
      "is_orphan": false,
      "meta": {
        "evidence": [
          {
            "reference": "PMID:33472202",
            "reference_title": "Acquired Angioedema with C1 Inhibitor Deficiency: Occurrence, Clinical Features, and Management: A Nationwide Retrospective Study in the Czech Republic Patients.",
            "snippet": "All patients responded to the acute attack treatment with icatibant and plasma-derived or recombinant C1 inhibitor concentrate.",
            "supports": "SUPPORT"
          }
        ],
        "evidence_count": 1,
        "therapeutic_agents": [
          "icatibant"
        ]
      },
      "node_type": "treatment"
    },
    {
      "color": "#fce7f3",
      "description": "C1-INH replacement is used for acute attacks and acts upstream by replacing deficient inhibitor activity.",
      "id": "Plasma-Derived or Recombinant C1 Inhibitor Concentrate",
      "is_orphan": false,
      "meta": {
        "evidence": [
          {
            "reference": "PMID:30866985",
            "reference_title": "Angioedema due to acquired C1-inhibitor deficiency: spectrum and treatment with C1-inhibitor concentrate.",
            "snippet": "A total of 3553 (97.7%) of the 3636 attacks were effectively treated with pdC1-INH as assessed by the patient.",
            "supports": "SUPPORT"
          },
          {
            "reference": "PMID:33472202",
            "reference_title": "Acquired Angioedema with C1 Inhibitor Deficiency: Occurrence, Clinical Features, and Management: A Nationwide Retrospective Study in the Czech Republic Patients.",
            "snippet": "All patients responded to the acute attack treatment with icatibant and plasma-derived or recombinant C1 inhibitor concentrate.",
            "supports": "SUPPORT"
          }
        ],
        "evidence_count": 2
      },
      "node_type": "treatment"
    },
    {
      "color": "#fce7f3",
      "description": "Tranexamic acid is an antifibrinolytic used as long-term prophylaxis in acquired C1-INH deficiency, with cohort evidence of benefit in many treated patients.",
      "id": "Tranexamic Acid Long-Term Prophylaxis",
      "is_orphan": false,
      "meta": {
        "evidence": [
          {
            "reference": "PMID:28284781",
            "reference_title": "Diagnosis, Course, and Management of Angioedema in Patients With Acquired C1-Inhibitor Deficiency.",
            "snippet": "Thirty-four patients received long-term prophylaxis with tranexamic acid (effective in 29) and 20 with androgens (effective in 8).",
            "supports": "SUPPORT"
          }
        ],
        "evidence_count": 1,
        "therapeutic_agents": [
          "tranexamic acid"
        ]
      },
      "node_type": "treatment"
    },
    {
      "color": "#fce7f3",
      "description": "Evaluation and treatment of the associated lymphoid malignancy or related disorder can reduce angioedema activity and may normalize complement parameters.",
      "id": "Treat Underlying Lymphoproliferative Disease",
      "is_orphan": false,
      "meta": {
        "evidence": [
          {
            "reference": "PMID:33472202",
            "reference_title": "Acquired Angioedema with C1 Inhibitor Deficiency: Occurrence, Clinical Features, and Management: A Nationwide Retrospective Study in the Czech Republic Patients.",
            "snippet": "In 6 of 7 patients (86%) treated for lymphoma, either a reduction in the frequency of angioedema attacks or both angioedema symptoms' disappearance and complement parameter normalization was observed.",
            "supports": "SUPPORT"
          }
        ],
        "evidence_count": 1
      },
      "node_type": "treatment"
    }
  ],
  "orphan_targets": []
}